pytest_doctest_mkdocstring/patch_doctest.py
pytest_doctest_mkdocstring-0.0.3.dist-info/METADATA
pytest_doctest_mkdocstring-0.0.3.dist-info/WHEEL
pytest_doctest_mkdocstring-0.0.3.dist-info/entry_points.txt
pytest_doctest_mkdocstring-0.0.3.dist-info/top_level.txt
pytest_doctest_mkdocstring-0.0.3.dist-info/RECORD
