Metadata-Version: 2.1
Name: pytest-doctest-mkdocstring
Version: 0.0.3
Summary: Run pytest --doctest-modules with markdown docstrings (code blocks)
Author: Mike Foster
Project-URL: Homepage, https://github.com/MusicalNinjaDad/pytest-doctest-mkdocstring
Project-URL: Repository, https://github.com/MusicalNinjaDad/pytest-doctest-mkdocstring
Project-URL: Issues, https://github.com/MusicalNinjaDad/pytest-doctest-mkdocstring/issues
Classifier: Programming Language :: Python :: 3
Classifier: License :: OSI Approved :: MIT License
Classifier: Operating System :: OS Independent
Classifier: Framework :: Pytest
Classifier: Intended Audience :: Developers
Classifier: Natural Language :: English
Requires-Python: >=3.7
